src/__init__.py
src/meteplanet_room_chat/__init__.py
src/meteplanet_room_chat/client.py
src/meteplanet_room_chat/config.py
src/meteplanet_room_chat/handlers.py
tests/connect.test.py
meteplanet_room_chat-0.0.2.dist-info/METADATA
meteplanet_room_chat-0.0.2.dist-info/WHEEL
meteplanet_room_chat-0.0.2.dist-info/top_level.txt
meteplanet_room_chat-0.0.2.dist-info/RECORD
